pysegmentation/__init__.py
pysegmentation/decomposition.py
pysegmentation/pipeline/build_feature_pipeline.py
pysegmentation/pipeline/factory.py
pysegmentation/preprocessing.py
pysegmentation/segmentation.py
pysegmentation/utils.py
pysegmentation/viz.py
pysegmentation-0.1.1.dist-info/LICENSE
pysegmentation-0.1.1.dist-info/METADATA
pysegmentation-0.1.1.dist-info/WHEEL
pysegmentation-0.1.1.dist-info/RECORD
