Metadata-Version: 2.1
Name: pysegmentation
Version: 0.1.1
Summary: Customer Segmentation
License: MIT
Author: Lê Huỳnh Đức
Author-email: lhduc94@gmail.com
Requires-Python: >=3.12,<3.13
Classifier: License :: OSI Approved :: MIT License
Classifier: Programming Language :: Python :: 3
Classifier: Programming Language :: Python :: 3.12
Requires-Dist: dython (>=0.7.9,<0.8.0)
Requires-Dist: kmodes (>=0.12.2,<0.13.0)
Requires-Dist: numpy (==1.26)
Requires-Dist: openpyxl (>=3.1.5,<4.0.0)
Requires-Dist: pandas (>=2.3.0,<3.0.0)
Requires-Dist: pyaml (>=25.5.0,<26.0.0)
Requires-Dist: scikit-learn (>=1.7.0,<2.0.0)
Requires-Dist: seaborn (>=0.13.2,<0.14.0)
Requires-Dist: setuptools (>=80.9.0,<81.0.0)
Requires-Dist: yellowbrick (>=1.5,<2.0)
Project-URL: repository, https://github.com/datasciencedances/pycusseg
